{
  "task": "rollup-optional-dependency-fix",
  "status": "completed",
  "iteration": 3,
  "maxIterations": 3,
  "currentPhase": "complete",
  "cycles": [
    {
      "id": 1,
      "name": "grounding-and-install-repair",
      "status": "completed"
    },
    {
      "id": 2,
      "name": "verification-and-fix",
      "status": "completed"
    },
    {
      "id": 3,
      "name": "architect-review-deslop-regression",
      "status": "completed"
    }
  ],
  "notes": [
    "Lockfile already included the Windows Rollup package while node_modules was missing it.",
    "Clean reinstall restored node_modules/@rollup/rollup-win32-x64-msvc and resolved the Rollup startup crash.",
    "Verified npm run dev:vite, npm run dev, npm run build, and npm test after reinstall.",
    "Architect review approved the install-state repair with no remaining Rollup findings.",
    "Deslop pass was a bounded no-op because this session changed only package-lock.json plus Ralph artifacts."
  ]
}
